{
    "tlb_if": [
        "tlb_if",
        "T7FQ7",
        "module"
    ],
    "...MASTER...": [
        "SIM",
        "amcQw",
        "module"
    ],
    "_vcs_unit__2052839234": [
        "_vcs_unit__2052839234",
        "R0N9w",
        "module"
    ],
    "_vcs_DPI_package": [
        "_vcs_DPI_package",
        "uM9F1",
        "module"
    ],
    "uvm_custom_install_recording": [
        "uvm_custom_install_recording",
        "nhiwz",
        "module"
    ],
    "_vcs_msglog": [
        "_vcs_msglog",
        "zQBzV",
        "module"
    ],
    "vcs_paramclassrepository": [
        "vcs_paramclassrepository",
        "hEeZs",
        "module"
    ],
    "std": [
        "std",
        "reYIK",
        "module"
    ],
    "top": [
        "top",
        "Emx8S",
        "module"
    ],
    "uvm_custom_install_verdi_recording": [
        "uvm_custom_install_verdi_recording",
        "EbjT3",
        "module"
    ],
    "uvm_pkg": [
        "uvm_pkg",
        "zr7M1",
        "module"
    ],
    "comb_tlb_if": [
        "comb_tlb_if",
        "HR983",
        "module"
    ],
    "config_pkg": [
        "config_pkg",
        "nUQt0",
        "module"
    ],
    "cva6_shared_tlb_sv32_0000": [
        "cva6_shared_tlb_sv32_0000",
        "a0W5G",
        "module"
    ],
    "cva6_config_pkg": [
        "cva6_config_pkg",
        "QJsi0",
        "module"
    ],
    "ariane_pkg": [
        "ariane_pkg",
        "eEMMZ",
        "module"
    ],
    "riscv": [
        "riscv",
        "FtHG5",
        "module"
    ],
    "cf_math_pkg": [
        "cf_math_pkg",
        "N2nk1",
        "module"
    ],
    "shared_tlb_if": [
        "shared_tlb_if",
        "SWIMm",
        "module"
    ],
    "cva6_tlb_sv32": [
        "cva6_tlb_sv32",
        "bhirm",
        "module"
    ],
    "tc_sram_wrapper": [
        "tc_sram_wrapper",
        "Bhhjs",
        "module"
    ]
}